<?xml version="1.0" ?>
<Base_Layouts>
	<Base_Layout Name="MM07_Novus_Base" Absolute="true" Faction="NOVUS">
	
		<NOVUS_REMOTE_TERMINAL ZAngle="230.00"> 4028.30, 943.99 </NOVUS_REMOTE_TERMINAL>
		<NOVUS_POWER_ROUTER ZAngle="0.00"> 4180.41, 875.65 </NOVUS_POWER_ROUTER>
		
		<NOVUS_SIGNAL_TOWER ZAngle="0.00"> 4096.09, 786.64 </NOVUS_SIGNAL_TOWER>
		<NOVUS_INPUT_STATION ZAngle="125.00"> 4105.54, 730.93 </NOVUS_INPUT_STATION>
		<NOVUS_INPUT_STATION ZAngle="126.00"> 4317.19, 739.32 </NOVUS_INPUT_STATION>
		
		<NOVUS_SIGNAL_TOWER ZAngle="0.00"> 4112.38, 1029.93 </NOVUS_SIGNAL_TOWER>
		<NOVUS_ROBOTIC_ASSEMBLY ZAngle="224.00"> 4221.80, 1026.53 </NOVUS_ROBOTIC_ASSEMBLY>
		<NOVUS_VEHICLE_ASSEMBLY ZAngle="227.00"> 4044.69, 1098.86 </NOVUS_VEHICLE_ASSEMBLY>
		<NOVUS_SIGNAL_TOWER ZAngle="0.00"> 3960.98, 1032.34 </NOVUS_SIGNAL_TOWER>
		<NOVUS_AIRCRAFT_ASSEMBLY ZAngle="0.00"> 3872.81, 1011.10 </NOVUS_AIRCRAFT_ASSEMBLY>
		<NOVUS_SIGNAL_TOWER ZAngle="0.00"> 3948.81, 754.62 </NOVUS_SIGNAL_TOWER>
		<NOVUS_SCIENCE_LAB ZAngle="0.00"> 3907.24, 688.64 </NOVUS_SCIENCE_LAB>
		
		
		<NOVUS_SIGNAL_TOWER ZAngle="0.00"> 4176.57, 1257.49 </NOVUS_SIGNAL_TOWER>
		<NOVUS_REDIRECTION_TURRET ZAngle="0.00"> 4264.04, 1254.84 </NOVUS_REDIRECTION_TURRET>
		<NOVUS_REDIRECTION_TURRET ZAngle="0.00"> 4099.56, 1274.33 </NOVUS_REDIRECTION_TURRET>
		<NOVUS_SIGNAL_TOWER ZAngle="0.00"> 4029.24, 1265.92 </NOVUS_SIGNAL_TOWER>
		<NOVUS_REDIRECTION_TURRET ZAngle="0.00"> 3951.89, 1301.76 </NOVUS_REDIRECTION_TURRET>
		<NOVUS_SIGNAL_TOWER ZAngle="273.34"> 3875.18, 1282.50 </NOVUS_SIGNAL_TOWER>
		<NOVUS_REDIRECTION_TURRET ZAngle="0.00"> 3794.88, 1320.65 </NOVUS_REDIRECTION_TURRET>
		
		<!--jdg cutting (for now)
		<NOVUS_SIGNAL_TOWER ZAngle="64.90"> 3755.76, 756.57 </NOVUS_SIGNAL_TOWER>
		<NOVUS_SUPERWEAPON_EMP ZAngle="0.00"> 3652.41, 720.12 </NOVUS_SUPERWEAPON_EMP>-->
	</Base_Layout>
</Base_Layouts>