<?xml version="1.0"?>
<Masari_INF_Avenger_XML>

  <!-- **************************************************************************************** -->
  <!-- *** UNIT(S) **************************************************************************** -->
  <!-- **************************************************************************************** -->

  <!-- This is just a base class... we never ever create an instance of it in the game.  -->
  <!-- - Oksana Kubushyna -->
  <X13_Masari_Units Name="Masari_Avenger">

    <Text_ID>TEXT_UNIT_MASARI_AVENGER_ENFORCER</Text_ID>

    <!-- ART -->
    <Land_Model_Name> ZI_Avenger_Male.ALO </Land_Model_Name>
    <Scale_Factor>1.15</Scale_Factor>
    <Loop_Idle_Anim_00>No</Loop_Idle_Anim_00>
    <!--  <SurfaceFX_Name>Masari_Avenger_Footprint</SurfaceFX_Name> -->
    <Occlusion_Silhouette_Enabled>1</Occlusion_Silhouette_Enabled>
    <Mouse_Collide_Override_Sphere_Radius> 10.0 </Mouse_Collide_Override_Sphere_Radius>
    <AssetBank> BANK_MASARI </AssetBank>

    <!-- INTERFACE -->
    <Icon_Name> i_icon_mi_avenger.tga  </Icon_Name>
    <GUI_Scene_Name> HealthBar_Scene_Small </GUI_Scene_Name>
    <GUI_Receives_Input> false </GUI_Receives_Input>
    <GUI_Min_Scale> 0.3 </GUI_Min_Scale>
    <GUI_Max_Scale> 2.5 </GUI_Max_Scale>
    <GUI_Default_Scale> 0.5 </GUI_Default_Scale>
    <GUI_World_Offset> 0.0, 0.0, -10 </GUI_World_Offset>
    <Select_Box_Scale>20</Select_Box_Scale>
    <Select_Box_Z_Adjust>3.0f</Select_Box_Z_Adjust>

    <!-- ATTRIBUTES -->
    <LOD_Bias>16</LOD_Bias>
    <Affiliation> Masari </Affiliation>
    <Victory_Relevant> No </Victory_Relevant>
    <CategoryMask> Small, Organic, CanAttack, RadiationHurts </CategoryMask>
    <Weather_Category>Infantry</Weather_Category>
    <Can_Fall_From_Bridge> true </Can_Fall_From_Bridge>
    <Importance> 0.2 </Importance>
    <Shot_Type> Infantry </Shot_Type>

    <Attributes SubObjectList="Yes">
		<Can_Ride_In_Vehicles> true </Can_Ride_In_Vehicles>
		<Is_Rebuildable_Avenger> true </Is_Rebuildable_Avenger>
		<Is_Immune_To_Virus> true </Is_Immune_To_Virus>
		<Is_Immune_To_Amplifier_Lockdown> true </Is_Immune_To_Amplifier_Lockdown>
		<Can_Garrison_Buildings> true </Can_Garrison_Buildings>
		<Tactical_Build_Cost_Credits />
		<DMA_Max> 150 </DMA_Max>
		<DMA_Regen_Rate> 5 </DMA_Regen_Rate>
		 <Tactical_Sell_Percent_Modifier> -0.5 </Tactical_Sell_Percent_Modifier>
		 <Tactical_Sell_Time_Seconds> 2.0 </Tactical_Sell_Time_Seconds>
	 </Attributes>

    <!-- MOVEMENT -->
    <MovementClass> Infantry </MovementClass>
    <Max_Speed>1.6</Max_Speed>
    <Max_Rate_Of_Turn>30.0</Max_Rate_Of_Turn>
    <Stopped_Rate_Of_Turn> 12.0 </Stopped_Rate_Of_Turn>
    <Custom_Soft_Footprint_Radius> 3.5 </Custom_Soft_Footprint_Radius>
    <Custom_Hard_XExtent> 2.0 </Custom_Hard_XExtent>
    <Custom_Hard_YExtent> 2.0 </Custom_Hard_YExtent>
    <Space_Layer> LandDynamic </Space_Layer>
    <UnitCollisionClass> Infantry </UnitCollisionClass>
    <FormationSpacing> .5 </FormationSpacing>
    <FormationRaggedness> 1 </FormationRaggedness>
    <MaxJiggleDistance> 2.0 </MaxJiggleDistance>
    <OverrideAcceleration> .05 </OverrideAcceleration>
    <OverrideDeceleration> .05 </OverrideDeceleration>
    <FormationOrder> 2 </FormationOrder>
    <Movement_Animation_Speed> 1.6 </Movement_Animation_Speed>
    <Rotation_Animation_Speed> 20.0 </Rotation_Animation_Speed>
    <Walk_Animation_Speed>.5</Walk_Animation_Speed>
    <OccupationStyle>1x1</OccupationStyle>
    <Strafe_Max_Speed_Coefficient> 0.8 </Strafe_Max_Speed_Coefficient>
    <Backpedal_Max_Speed_Coefficient> 0.8 </Backpedal_Max_Speed_Coefficient>
    <Strafe_Animation_Speed> 0.8 </Strafe_Animation_Speed>
    <Backpedal_Animation_Speed> 0.8 </Backpedal_Animation_Speed>
    <Should_Move_Anim_Lockout_Attack_Anim> true </Should_Move_Anim_Lockout_Attack_Anim>

    <!-- CONFLICT -->
    <Is_Attackable> true </Is_Attackable>
    <Ranged_Target_Z_Adjust>7.0</Ranged_Target_Z_Adjust>
    <Collidable_By_Projectile_Living>Yes</Collidable_By_Projectile_Living>
    <Land_FOW_Reveal_Range>120.0</Land_FOW_Reveal_Range>
    <Attack_Category_Restrictions> Flying | Resource | Resource_INST </Attack_Category_Restrictions>

    <Tactical_Health> 190 </Tactical_Health>

    <!-- BEHAVIORS -->

    <LandBehavior>
		 EFFECT_GENERATOR,
		 EFFECT_REGISTRY,
		 ATTRIBUTE_DIRECTORY,
		 SELECTABLE,
		 RADAR_MAP_VISIBLE,
		 GUI,
		 SURFACE_FX,
		 WALK_LOCOMOTOR,
		 FORMATION,
		 IDLE,
		 TARGETING,
		 TURRET,
		 WEAPON,
		 REVEAL,
     SQUASH,
		 HIDE_WHEN_FOGGED,
		 BALLISTIC,
		 ABILITY_COUNTDOWN
		 SWITCH_TYPE,
		 AI_RECRUITABLE,
		 DAMAGE_TRACKING,
		 AI_TARGET,
		 TACTICAL_SELL,
		 TELEPORT_PAD,
		 <!-- ELEMENTAL_MODE must be last because it causes add behavior to be called -->
      ELEMENTAL_MODE
    </LandBehavior>

    <BehaviorType Name="TooltipBehaviorType">
      <Tooltip_Category> TEXT_TOOLTIP_CATEGORY_INFANTRY </Tooltip_Category>
		 <Tooltip_Good_Against> TEXT_TYPE_VERSUS_INFANTRY </Tooltip_Good_Against>
		 <Tooltip_Vulnerable_To> TEXT_TYPE_VERSUS_AIR_UNITS TEXT_TYPE_VERSUS_GROUND_UNITS </Tooltip_Vulnerable_To>
    </BehaviorType>

         <Researched_Upgrades>
		TEXT_MASARI_RESEARCH_TITLE_DARK_MATTER_AFINITY
		TEXT_MASARI_RESEARCH_TITLE_DARK_MATTER_MASTERY
		TEXT_MASARI_RESEARCH_TITLE_RECONSTRUCTION
		TEXT_MASARI_RESEARCH_TITLE_CLEANSING_ENERGY
         </Researched_Upgrades>
	 
    <BehaviorType Name="ArmorAndDamageBehaviorType">
      <Armor_Type> Armor_Masari_Infantry_Light </Armor_Type>
    </BehaviorType>

    <BehaviorType name="AIBehaviorType">
      <AI_Combat_Power> 1 </AI_Combat_Power>
      <Idle_Chase_Range> 20.0 </Idle_Chase_Range> <!-- Double click guard area Keep very small-->
      <Guard_Chase_Range> 135.0 </Guard_Chase_Range> <!-- Guard radius for unit-->
      <Autonomous_Move_Extension_Vs_Attacker> 20.0 </Autonomous_Move_Extension_Vs_Attacker> <!--Range outside of guard area unit will move-->
      <Attack_Move_Response_Range> 50.0 </Attack_Move_Response_Range>  <!-- When given a attack move command unit will travel this distance from path to attack-->
      <AI_Target_Level>Group_Member</AI_Target_Level>
		 <Attack_Score_Rating> 0.7 </Attack_Score_Rating>
		 <Scout_Score_Rating> 0.1 </Scout_Score_Rating>
		 <Guerilla_Score_Rating> 0.0 </Guerilla_Score_Rating>
	 </BehaviorType>

    <BehaviorType Name="WeaponBehaviorType">
      <Can_Attack_Without_Weapon_Behavior>Yes</Can_Attack_Without_Weapon_Behavior>
      <Targeting_Stickiness_Time_Threshold>5.0</Targeting_Stickiness_Time_Threshold>
      <Targeting_Priority_Set> Masari_Avenger_Target_Priority </Targeting_Priority_Set>
      <Targeting_Fire_Inaccuracy> 1.0 </Targeting_Fire_Inaccuracy>
      <Targeting_Min_Attack_Distance> 0.0 </Targeting_Min_Attack_Distance>
      <Targeting_Max_Attack_Distance> 120.0 </Targeting_Max_Attack_Distance>
    </BehaviorType>

	  <BehaviorType NAme="LuaScriptBehaviorType">
		  <Lua_Only_Service_If_AI>True</Lua_Only_Service_If_AI>
		  <Lua_Land_Behaviors>Generic_Vehicle_Unit_Behavior,Defensive_AI_Unit_Behavior</Lua_Land_Behaviors>
		  <Lua_Script_Data>
			  GenericVehicle = {}
			  GenericVehicle.SearchRange = 150.0
			  GenericVehicle.KiteRange = 100.0
			  GenericVehicle.CrushRange = 0.0
			  DefensiveAI = {}
			  DefensiveAI.KillTurret = true
			  DefensiveAI.KillTurretRange = 40.0
		  </Lua_Script_Data>
	  </BehaviorType>

	  <BehaviorType Name="TurretBehaviorType">
      <Barrel_Bone_Name> Barrel </Barrel_Bone_Name>
      <Turret_Bone_Name> Turret </Turret_Bone_Name>
      <Turret_Rotate_Speed> 10.0 </Turret_Rotate_Speed>
      <Apply_Z_Turret_Rotate_To_Axis>2</Apply_Z_Turret_Rotate_To_Axis>
      <Apply_Y_Turret_Rotate_To_Axis>1</Apply_Y_Turret_Rotate_To_Axis>
      <Turret_Rotate_Extent_Degrees> 45.0 </Turret_Rotate_Extent_Degrees>
      <Turret_Elevate_Extent_Degrees> 50.0 </Turret_Elevate_Extent_Degrees>
      <Ground_Vehicle_Turret_Target> Yes </Ground_Vehicle_Turret_Target>
      <Ground_Infantry_Turret_Target> Yes </Ground_Infantry_Turret_Target>
      <Turret_XY_Only> false </Turret_XY_Only>
    </BehaviorType>

	  <BehaviorType Name="BuildableObjectBehaviorType">
		 <!-- values are for selling off -->
		  <Tactical_Build_Cost_Campaign> 2 </Tactical_Build_Cost_Campaign>
		  <Tactical_Build_Cost_Multiplayer> 2 </Tactical_Build_Cost_Multiplayer>
	  </BehaviorType>

	  <BehaviorType Name="TypeSwitchBehaviorType">
      <Switch_Effect_Generator_Name> MasariSwitchGenerator </Switch_Effect_Generator_Name>
    </BehaviorType>

    <BehaviorType Name="EncyclopediaBehaviorType">
      <Icon_Name> i_icon_mi_avenger.tga  </Icon_Name>
		<!-- For automated control groups by object type (playing with Game Controller), we typically use -->
		<!-- the Icon_Name. If there is a defined Control_Group_Icon_Name in XML, it will be used as an override. -->
		<Control_Group_Icon_Name> i_icon_mi_avenger.tga </Control_Group_Icon_Name>
    </BehaviorType>

    <BehaviorType Name="RadarMapBehaviorType">
      <Radar_Icon_Size>0.02  0.02</Radar_Icon_Size>
    </BehaviorType>

    <BehaviorType Name="BallisticBehaviorType">
      <Ballistic_Weight>3.0</Ballistic_Weight>
    </BehaviorType>

    <BehaviorType Name="BlobShadowBehaviorType">
      <Blob_Shadow_Below_Detail_Level>3</Blob_Shadow_Below_Detail_Level>
      <Blob_Shadow_Scale>10.0, 10.0</Blob_Shadow_Scale>
      <Blob_Shadow_Bone_Name>B_Chest</Blob_Shadow_Bone_Name>
      <Blob_Shadow_Below_Detail_Level>3</Blob_Shadow_Below_Detail_Level>
      <Blob_Shadow_Scale>5.0, 5.0</Blob_Shadow_Scale>
      <Blob_Shadow_Material_Name>Generic_Shadow</Blob_Shadow_Material_Name>
      <Blob_Shadow_Bone_Name>B_Chest</Blob_Shadow_Bone_Name>
      <No_Reflection_Below_Detail_Level>1</No_Reflection_Below_Detail_Level>
      <No_Refraction_Below_Detail_Level>1</No_Refraction_Below_Detail_Level>
    </BehaviorType>

    <BehaviorType Name="SFXBehaviorType">
          <SFXEvent_On_Create> None </SFXEvent_On_Create>
          <SFXEvent_Fire> </SFXEvent_Fire>
          <SFXEvent_Weapon_Firing_Loop> SFX_Masari_Flamethrower_Loop </SFXEvent_Weapon_Firing_Loop>
          <SFXEvent_Select>Unit_Select_Masari_Conqueror_Avenger</SFXEvent_Select>
          <SFXEvent_Move>Unit_Move_A_Masari_Conqueror_Avenger</SFXEvent_Move>
          <SFXEvent_Move_At_Top_Speed>Unit_Move_B_Masari_Conqueror_Avenger</SFXEvent_Move_At_Top_Speed>
          <SFXEvent_Attack>Unit_Attack_A_Masari_Conqueror_Avenger</SFXEvent_Attack>
          <SFXEvent_Attack_At_Top_Speed>Unit_Attack_B_Masari_Conqueror_Avenger</SFXEvent_Attack_At_Top_Speed>
          <SFXEvent_Turret_Rotating_Loop> </SFXEvent_Turret_Rotating_Loop>
          <Death_SFXEvent_Start_Die> Unit_Death_Masari_Male </Death_SFXEvent_Start_Die>
          <SFXEvent_Engine_Idle_Loop> </SFXEvent_Engine_Idle_Loop>
          <SFXEvent_Engine_Moving_Loop> </SFXEvent_Engine_Moving_Loop>
          <SFXEvent_Unit_Lost />
          <SFXEvent_Tactical_Build_Started>GUI_BUILD_Infantry</SFXEvent_Tactical_Build_Started>
          <SFXEvent_Tactical_Build_Complete>Unit_Select_Masari_Conqueror_Avenger</SFXEvent_Tactical_Build_Complete>
          <SFXEvent_Tactical_Build_Cancelled>GUI_BUILD_Infantry_Canceled</SFXEvent_Tactical_Build_Cancelled>

          <!-- Maria 05.01.2006 - Adding build sounds for Global production -->
          <SFXEvent_Build_Started>GUI_BUILD_Infantry</SFXEvent_Build_Started>
          <SFXEvent_Build_Complete>Unit_Select_Masari_Conqueror_Avenger</SFXEvent_Build_Complete>
          <SFXEvent_Build_Cancelled>GUI_BUILD_Infantry_Canceled</SFXEvent_Build_Cancelled>
       </BehaviorType>

    <BehaviorType Name="GUIBehaviorType">
       <GUI_Bracket_Size>2</GUI_Bracket_Size>
       <GUI_Bounds_Scale>0.5</GUI_Bounds_Scale>
       <!-- Maria 05.18.2006 - Data needed for the models attached to the mouse in Global -->
       <GUI_Is_Top_View> No </GUI_Is_Top_View>
       <GUI_Rotate_Angle_Degrees> 0.0 </GUI_Rotate_Angle_Degrees>
       <GUI_Is_Model_Shifted_Down> Yes </GUI_Is_Model_Shifted_Down>
       <GUI_Shift_Factor> 4.7 </GUI_Shift_Factor>
       <GUI_Strategic_Mode_Scale> 0.15 </GUI_Strategic_Mode_Scale>
    </BehaviorType>

    <BehaviorType Name="DeathFXBehaviorType">
       <Specific_Death_Anim_Type> DIE </Specific_Death_Anim_Type>
       <!--<Death_Clone> Damage_Default, Masari_Avenger_Death_Clone_Resource </Death_Clone>-->
       <Death_Spawn> Damage_Alien_AE_Radiation, Alien_Mutant_Slave </Death_Spawn>
       <Death_Spawn> Damage_Alien_AE_Radiation, Alien_Mutant_Slave_02 </Death_Spawn>
       <Death_Spawn> Damage_Alien_AE_Radiation, Alien_Mutant_Slave_03 </Death_Spawn>
		 <Death_Spawn> Damage_Alien_Mutant_Slave_Claws, Alien_Mutant_Slave </Death_Spawn>
		 <Death_Spawn> Damage_Alien_Mutant_Slave_Claws, Alien_Mutant_Slave_02 </Death_Spawn>
		 <Death_Spawn> Damage_Alien_Mutant_Slave_Claws, Alien_Mutant_Slave_03 </Death_Spawn>
       <Death_Clone>Damage_Novus_Amplifier_Sonic_Resonance, Disintegrate_Death_Clone</Death_Clone>
       <Death_Fade_Time>.25</Death_Fade_Time>
       <Death_Persistence_Duration>30</Death_Persistence_Duration>
       <Death_Speed_Min>1.0</Death_Speed_Min>
       <Death_Speed_Max>2.0</Death_Speed_Max>
    </BehaviorType>

    <BehaviorType Name="CrushBehaviorType">
       <Crush_Defense> 10 </Crush_Defense>
       <Crush_Power> 4 </Crush_Power>
    </BehaviorType>

    <BehaviorType Name="FleetBehaviorType">
       <!-- Maria 05.24.2006 - How much space does the unit take up -->
       <Unit_Pop_Cap> 1 </Unit_Pop_Cap>
    </BehaviorType>

    <BehaviorType Name="TeleportPadBehaviorType">
       <Teleporter_Access_Types> ALIEN_RELOCATOR </Teleporter_Access_Types>
    </BehaviorType>

    <Unit_Abilities_Data SubObjectList="Yes">

       <Unit_Ability Name="Enter_Sentry_Unit_Ability">
          <Targeting_Type> ALLY_OBJECT </Targeting_Type>
          <Type>EFFECT_GENERATOR</Type>
          <GUI_Activated_Ability_Name> Enter_Sentry_Special_Ability </GUI_Activated_Ability_Name>
          <Effect_Generator_Name> Enter_Sentry_Effect_Generator </Effect_Generator_Name>
       </Unit_Ability>

    </Unit_Abilities_Data>

    <Abilities SubObjectList="Yes">

       <Effect_Generator_Ability Name="Enter_Sentry_Special_Ability">

          <Activation_Min_Range> 0 </Activation_Min_Range>
          <Activation_Max_Range> 20 </Activation_Max_Range>
          <Effect_Generator_Name> Enter_Sentry_Effect_Generator </Effect_Generator_Name>
          <Activation_Style> SPECIAL_ATTACK </Activation_Style>
          <Can_Target_Enemies>No</Can_Target_Enemies>
          <Can_Target_Allies>Yes</Can_Target_Allies>
          <Can_Target_Neutral>No</Can_Target_Neutral>

          <Applicable_Unit_Types>
             Masari_Sentry,
             Masari_Sentry_Fire,
             Masari_Sentry_Ice,
          </Applicable_Unit_Types>

       </Effect_Generator_Ability>

    </Abilities>

    <Effect_Generator_Data SubObjectList="Yes">

       <Effect_Generator Name="MasariSwitchGenerator">
          <Should_Deactivate_Manually> false </Should_Deactivate_Manually>
          <Is_Independent_Generator>Yes</Is_Independent_Generator>

          <Effect_Generator_Entry Name="Entry1">
             <Duration> 1.0 </Duration>
             <Effect_Name> MasariSwitchCleanseEffect </Effect_Name>
             <Target_Gathering_Mask> Self </Target_Gathering_Mask>
          </Effect_Generator_Entry>

          <Effect_Generator_Entry Name="Entry2">
             <Duration> 0.5 </Duration>
             <Base_Delay> 0.4 </Base_Delay>
             <Effect_Name> MasariFullArmorEffect </Effect_Name>
             <Target_Gathering_Mask> Self </Target_Gathering_Mask>
             <!-- only in ice mode -->
             <Target_Filter_C> In_Ice_Mode </Target_Filter_C>
          </Effect_Generator_Entry>

       </Effect_Generator>


       <Effect_Generator Name="RegenerateParentGenerator">

          <Effect_Generator_Entry Name="Entry1">
             <Effect_Name> RegenerateAvengerEffect </Effect_Name>
             <Duration> -1.0 </Duration>
             <Target_Gathering_Mask> Self </Target_Gathering_Mask>
          </Effect_Generator_Entry>

       </Effect_Generator>
    </Effect_Generator_Data>

 </X13_Masari_Units>


 <!-- Male variant of Avenger -->
 <X13_Masari_Units Name="Masari_Male_Avenger">
    <Variant_Of_Existing_Type> Masari_Avenger </Variant_Of_Existing_Type>
    <Land_Model_Name> ZI_Avenger_Male.ALO </Land_Model_Name>

    <BehaviorType Name="DeathFXBehaviorType">
       <!--<Death_Clone> Damage_Default, Masari_Avenger_Death_Clone_Resource </Death_Clone>-->
       <Death_Spawn> Damage_Alien_AE_Radiation, Alien_Mutant_Slave </Death_Spawn>
       <Death_Spawn> Damage_Alien_AE_Radiation, Alien_Mutant_Slave_02 </Death_Spawn>
       <Death_Spawn> Damage_Alien_AE_Radiation, Alien_Mutant_Slave_03 </Death_Spawn>
       <Death_Clone>Damage_Novus_Amplifier_Sonic_Resonance, Disintegrate_Death_Clone</Death_Clone>
    </BehaviorType>

    <Effect_Generator_Data SubObjectList="Yes" Replace="No">

       <Effect_Generator Name="Enter_Sentry_Effect_Generator">
          <Should_Deactivate_Manually> false </Should_Deactivate_Manually>
          <Is_Independent_Generator>Yes</Is_Independent_Generator>

          <Effect_Generator_Entry Name="Entry1">
             <Effect_Name> Male_Avenger_Enter_Sentry_Effect </Effect_Name>
             <Deactivate_Parent_If_Idle>yes</Deactivate_Parent_If_Idle>
             <Target_Gathering_Mask> Target </Target_Gathering_Mask>
             <Target_Filter_C> Can_Enter_Vehicle </Target_Filter_C>

          </Effect_Generator_Entry>
       </Effect_Generator>

    </Effect_Generator_Data>

 </X13_Masari_Units>



 <!-- Female variant of Avenger -->
 <X13_Masari_Units Name="Masari_Female_Avenger">
    <Variant_Of_Existing_Type> Masari_Avenger </Variant_Of_Existing_Type>
    <Land_Model_Name> ZI_Avenger_Female.ALO </Land_Model_Name>

    <BehaviorType Name="DeathFXBehaviorType">
       <!--<Death_Clone> Damage_Default, Masari_Avenger_Female_Death_Clone_Resource </Death_Clone>-->
       <Death_Spawn> Damage_Alien_AE_Radiation, Alien_Mutant_Slave </Death_Spawn>
       <Death_Spawn> Damage_Alien_AE_Radiation, Alien_Mutant_Slave_02 </Death_Spawn>
       <Death_Spawn> Damage_Alien_AE_Radiation, Alien_Mutant_Slave_03 </Death_Spawn>
       <Death_Clone>Damage_Novus_Amplifier_Sonic_Resonance, Disintegrate_Death_Clone</Death_Clone>
    </BehaviorType>

    <Effect_Generator_Data SubObjectList="Yes" Replace="No">

       <Effect_Generator Name="Enter_Sentry_Effect_Generator">
          <Should_Deactivate_Manually> false </Should_Deactivate_Manually>
          <Is_Independent_Generator>Yes</Is_Independent_Generator>

          <Effect_Generator_Entry Name="Entry1">
             <Effect_Name> Female_Avenger_Enter_Sentry_Effect </Effect_Name>
             <Deactivate_Parent_If_Idle>yes</Deactivate_Parent_If_Idle>
             <Target_Gathering_Mask> Target </Target_Gathering_Mask>
             <Target_Filter_C> Can_Enter_Vehicle </Target_Filter_C>
          </Effect_Generator_Entry>
       </Effect_Generator>

    </Effect_Generator_Data>
 </X13_Masari_Units>



 <!-- **************************************************************************************** -->
 <!-- *** VARIANTS *************************************************************************** -->
 <!-- **************************************************************************************** -->

 <!-- **************************************************************************************** -->
 <!-- *****                              FIGMENT                                     ********* -->
 <!-- **************************************************************************************** -->
 <X13_Masari_Units Name="Masari_Avenger_Figment">
    <Variant_Of_Existing_Type> Masari_Female_Avenger </Variant_Of_Existing_Type>

    <!-- TEXT -->
    <Text_ID>TEXT_UNIT_MASARI_AVENGER_FIGMENT</Text_ID>


    <!-- ATTRIBUTES -->
    <Attributes SubObjectList="Yes">
       <Regenerate_Type>Masari_Figment</Regenerate_Type>
    </Attributes>


    <BehaviorType Name="TooltipBehaviorType">
       <Tooltip_Description_Text_ID> TEXT_TOOLTIP_DESCRIPTION_MASARI_AVENGER_FIGMENT_LIGHT </Tooltip_Description_Text_ID>
    </BehaviorType>


    <BehaviorType Name="ElementalModeType">
       <Elemental_Object_Types> Fire, Masari_Avenger_Figment_Fire </Elemental_Object_Types>
       <Elemental_Object_Types> Ice, Masari_Avenger_Figment_Ice </Elemental_Object_Types>
    </BehaviorType>

    <BehaviorType Name="TypeSwitchBehaviorType">
       <!-- List of types this object can switch to - This is mainly needed to inforce build limits and must be
						      only added to the base type used for production dependencies purposes -->
       <Type_Switch_Types> Masari_Avenger_Figment_Fire, Masari_Avenger_Figment_Ice  </Type_Switch_Types>
       <Switch_Effect_Generator_Name> MasariSwitchGenerator </Switch_Effect_Generator_Name>
    </BehaviorType>

    <BehaviorType Name="SFXBehaviorType">
		 <SFXEvent_On_Create> Unit_Select_Masari_Figment_Avenger</SFXEvent_On_Create>
		 <SFXEvent_Fire> SFX_Masari_Infantry_Fire </SFXEvent_Fire>
       <SFXEvent_Weapon_Firing_Loop>  </SFXEvent_Weapon_Firing_Loop>
       <SFXEvent_Select>Unit_Select_Masari_Figment_Avenger</SFXEvent_Select>
       <SFXEvent_Move>Unit_Move_A_Masari_Figment_Avenger</SFXEvent_Move>
       <SFXEvent_Move_At_Top_Speed>Unit_Move_B_Masari_Figment_Avenger</SFXEvent_Move_At_Top_Speed>
       <SFXEvent_Attack>Unit_Attack_A_Masari_Figment_Avenger</SFXEvent_Attack>
       <SFXEvent_Attack_At_Top_Speed>Unit_Attack_B_Masari_Figment_Avenger</SFXEvent_Attack_At_Top_Speed>
       <SFXEvent_Turret_Rotating_Loop> </SFXEvent_Turret_Rotating_Loop>
       <Death_SFXEvent_Start_Die> Unit_Death_Masari_Female </Death_SFXEvent_Start_Die>
       <SFXEvent_Engine_Idle_Loop> </SFXEvent_Engine_Idle_Loop>
       <SFXEvent_Engine_Moving_Loop> </SFXEvent_Engine_Moving_Loop>
       <SFXEvent_Unit_Lost />
       <SFXEvent_Tactical_Build_Started>GUI_BUILD_Infantry</SFXEvent_Tactical_Build_Started>
       <SFXEvent_Tactical_Build_Complete>Unit_Select_Masari_Figment_Avenger</SFXEvent_Tactical_Build_Complete>
       <SFXEvent_Tactical_Build_Cancelled>GUI_BUILD_Infantry_Canceled</SFXEvent_Tactical_Build_Cancelled>

       <!-- Maria 05.01.2006 - Adding build sounds for Global production -->
       <SFXEvent_Build_Started>GUI_BUILD_Infantry</SFXEvent_Build_Started>
       <SFXEvent_Build_Complete>Unit_Select_Masari_Figment_Avenger</SFXEvent_Build_Complete>
       <SFXEvent_Build_Cancelled>GUI_BUILD_Infantry_Canceled</SFXEvent_Build_Cancelled>
    </BehaviorType>

    <BehaviorType Name="DeathFXBehaviorType">
       <Death_Clone> Damage_Default, Masari_Avenger_Figment_Death_Clone_Resource </Death_Clone>
    </BehaviorType>
 </X13_Masari_Units>


 <X13_Masari_Units Name="Masari_Avenger_Figment_Fire">
    <Variant_Of_Existing_Type> Masari_Avenger_Figment </Variant_Of_Existing_Type>

    <!-- All avengers share this setup, so we'll include it - Oksana 05/21/2007 -->
    <!--INCLUDE ".\Data\XML\Includes\Masari_Avenger\MASARI_INF_Avenger_Light.xml" -->

 </X13_Masari_Units>


 <X13_Masari_Units Name="Masari_Avenger_Figment_Ice">
    <Variant_Of_Existing_Type> Masari_Avenger_Figment </Variant_Of_Existing_Type>

    <!-- All avengers share this setup, so we'll include it - Oksana 05/21/2007 -->
    <!--INCLUDE ".\Data\XML\Includes\Masari_Avenger\MASARI_INF_Avenger_Dark.xml" -->

 </X13_Masari_Units>

   <X13_Masari_Units Name="Masari_Avenger_Figment_Death_Clone_Resource">
      <Variant_Of_Existing_Type>Masari_Avenger_Figment</Variant_Of_Existing_Type>
      <Use_Base_Type_By_Default> false </Use_Base_Type_By_Default>
      <Is_Placed_By_Editor>false</Is_Placed_By_Editor>

      <CategoryMask> Resource_INST </CategoryMask>
      <LandBehavior>
         HIDE_WHEN_FOGGED,
         BALLISTIC,
         RESOURCE,
         EFFECT_REGISTRY,
         ATTRIBUTE_DIRECTORY
      </LandBehavior>

      <BehaviorType Name="ResourceBehaviorType">
         <Resource_Units> 8 </Resource_Units>
         <Resource_For_Faction> Alien, Alien_ZM06_KamalRex </Resource_For_Faction>
         <Is_Single_Resource> true </Is_Single_Resource>
         <Use_Death_Behavior> true </Use_Death_Behavior>
      </BehaviorType>

    <BehaviorType Name="SFXBehaviorType">
		 <SFXEvent_On_Create> None </SFXEvent_On_Create>
       <Death_SFXEvent_Start_Die> Unit_Death_Masari_Female </Death_SFXEvent_Start_Die>
    </BehaviorType>

   </X13_Masari_Units>



 <!-- **************************************************************************************** -->
 <!-- *****                              PEACEBRINGER                                ********* -->
 <!-- **************************************************************************************** -->
 <X13_Masari_Units Name="Masari_Avenger_Peacebringer">
    <Variant_Of_Existing_Type> Masari_Male_Avenger </Variant_Of_Existing_Type>

    <!-- TEXT -->
    <Text_ID>TEXT_UNIT_MASARI_AVENGER_PEACEBRINGER </Text_ID>

    <!-- ATTRIBUTES -->
    <Attributes SubObjectList="Yes">
       <Regenerate_Type>Masari_Peacebringer</Regenerate_Type>
    </Attributes>


    <BehaviorType Name="TooltipBehaviorType">
       <Tooltip_Description_Text_ID> TEXT_TOOLTIP_DESCRIPTION_MASARI_AVENGER_PEACEBRINGER_LIGHT </Tooltip_Description_Text_ID>
    </BehaviorType>


    <BehaviorType Name="ElementalModeType">
       <Elemental_Object_Types> Fire, Masari_Avenger_Peacebringer_Fire </Elemental_Object_Types>
       <Elemental_Object_Types> Ice, Masari_Avenger_Peacebringer_Ice </Elemental_Object_Types>
    </BehaviorType>

    <BehaviorType Name="TypeSwitchBehaviorType">
       <!-- List of types this object can switch to - This is mainly needed to inforce build limits and must be
						      only added to the base type used for production dependencies purposes -->
       <Type_Switch_Types> Masari_Avenger_Peacebringer_Fire, Masari_Avenger_Peacebringer_Ice  </Type_Switch_Types>
       <Switch_Effect_Generator_Name> MasariSwitchGenerator </Switch_Effect_Generator_Name>
    </BehaviorType>

    <BehaviorType Name="SFXBehaviorType">
      <SFXEvent_On_Create>Unit_Select_Masari_Peacebringer_Avenger</SFXEvent_On_Create>
      <SFXEvent_Fire> SFX_Masari_Infantry_Fire</SFXEvent_Fire>
      <SFXEvent_Weapon_Firing_Loop> </SFXEvent_Weapon_Firing_Loop>
      <SFXEvent_Select>Unit_Select_Masari_Peacebringer_Avenger</SFXEvent_Select>
      <SFXEvent_Move>Unit_Move_A_Masari_Peacebringer_Avenger</SFXEvent_Move>
      <SFXEvent_Move_At_Top_Speed>Unit_Move_B_Masari_Peacebringer_Avenger</SFXEvent_Move_At_Top_Speed>
      <SFXEvent_Attack>Unit_Attack_A_Masari_Peacebringer_Avenger</SFXEvent_Attack>
      <SFXEvent_Attack_At_Top_Speed>Unit_Attack_B_Masari_Peacebringer_Avenger</SFXEvent_Attack_At_Top_Speed>
      <SFXEvent_Turret_Rotating_Loop> </SFXEvent_Turret_Rotating_Loop>
      <Death_SFXEvent_Start_Die> Unit_Death_Masari_Male </Death_SFXEvent_Start_Die>
      <SFXEvent_Engine_Idle_Loop> </SFXEvent_Engine_Idle_Loop>
      <SFXEvent_Engine_Moving_Loop> </SFXEvent_Engine_Moving_Loop>
      <SFXEvent_Unit_Lost />
      <SFXEvent_Tactical_Build_Started>GUI_BUILD_Infantry</SFXEvent_Tactical_Build_Started>
      <SFXEvent_Tactical_Build_Complete>Unit_Select_Masari_Peacebringer_Avenger</SFXEvent_Tactical_Build_Complete>
      <SFXEvent_Tactical_Build_Cancelled>GUI_BUILD_Infantry_Canceled</SFXEvent_Tactical_Build_Cancelled>

      <!-- Maria 05.01.2006 - Adding build sounds for Global production -->
      <SFXEvent_Build_Started>GUI_BUILD_Infantry</SFXEvent_Build_Started>
      <SFXEvent_Build_Complete>Unit_Select_Masari_Peacebringer_Avenger</SFXEvent_Build_Complete>
      <SFXEvent_Build_Cancelled>GUI_BUILD_Infantry_Canceled</SFXEvent_Build_Cancelled>
    </BehaviorType>

    <BehaviorType Name="DeathFXBehaviorType">
       <Death_Clone> Damage_Default, Masari_Avenger_Peacebringer_Death_Clone_Resource </Death_Clone>
    </BehaviorType>
  </X13_Masari_Units>

  <X13_Masari_Units Name="Masari_Avenger_Peacebringer_Fire">
    <Variant_Of_Existing_Type> Masari_Avenger_Peacebringer </Variant_Of_Existing_Type>

    <!-- All avengers share this setup, so we'll include it - Oksana 05/21/2007 -->
    <!--INCLUDE ".\Data\XML\Includes\Masari_Avenger\MASARI_INF_Avenger_Light.xml" -->

  </X13_Masari_Units>


  <X13_Masari_Units Name="Masari_Avenger_Peacebringer_Ice">
    <Variant_Of_Existing_Type> Masari_Avenger_Peacebringer </Variant_Of_Existing_Type>

    <!-- All avengers share this setup, so we'll include it - Oksana 05/21/2007 -->
    <!--INCLUDE ".\Data\XML\Includes\Masari_Avenger\MASARI_INF_Avenger_Dark.xml" -->

  </X13_Masari_Units>



   <X13_Masari_Units Name="Masari_Avenger_Peacebringer_Death_Clone_Resource">
      <Variant_Of_Existing_Type>Masari_Avenger_Peacebringer</Variant_Of_Existing_Type>
      <Use_Base_Type_By_Default> false </Use_Base_Type_By_Default>
      <Is_Placed_By_Editor>false</Is_Placed_By_Editor>

      <CategoryMask> Resource_INST </CategoryMask>
      <LandBehavior>
         HIDE_WHEN_FOGGED,
         BALLISTIC,
         RESOURCE,
         EFFECT_REGISTRY,
         ATTRIBUTE_DIRECTORY
      </LandBehavior>

      <BehaviorType Name="ResourceBehaviorType">
         <Resource_Units> 10 </Resource_Units>
         <Resource_For_Faction> Alien, Alien_ZM06_KamalRex </Resource_For_Faction>
         <Is_Single_Resource> true </Is_Single_Resource>
         <Use_Death_Behavior> true </Use_Death_Behavior>
      </BehaviorType>

    <BehaviorType Name="SFXBehaviorType">
		 <SFXEvent_On_Create> None </SFXEvent_On_Create>
       <Death_SFXEvent_Start_Die> Unit_Death_Masari_Male </Death_SFXEvent_Start_Die>
    </BehaviorType>

   </X13_Masari_Units>


  <!-- **************************************************************************************** -->
  <!-- *****                              SEEKER                                      ********* -->
  <!-- **************************************************************************************** -->
  <X13_Masari_Units Name="Masari_Avenger_Seeker">
    <Variant_Of_Existing_Type> Masari_Male_Avenger </Variant_Of_Existing_Type>

    <!-- TEXT -->
    <Text_ID>TEXT_UNIT_MASARI_AVENGER_SEEKER </Text_ID>


    <!-- ATTRIBUTES -->
    <Attributes SubObjectList="Yes">
      <Regenerate_Type>Masari_Seeker</Regenerate_Type>
    </Attributes>


    <BehaviorType Name="TooltipBehaviorType">
      <Tooltip_Description_Text_ID> TEXT_TOOLTIP_DESCRIPTION_MASARI_AVENGER_SEEKER_LIGHT </Tooltip_Description_Text_ID>
    </BehaviorType>


    <BehaviorType Name="ElementalModeType">
      <Elemental_Object_Types> Fire, Masari_Avenger_Seeker_Fire </Elemental_Object_Types>
      <Elemental_Object_Types> Ice, Masari_Avenger_Seeker_Ice </Elemental_Object_Types>
    </BehaviorType>

    <BehaviorType Name="TypeSwitchBehaviorType">
      <!-- List of types this object can switch to - This is mainly needed to inforce build limits and must be
						      only added to the base type used for production dependencies purposes -->
      <Type_Switch_Types> Masari_Avenger_Seeker_Fire, Masari_Avenger_Seeker_Ice  </Type_Switch_Types>
      <Switch_Effect_Generator_Name> MasariSwitchGenerator </Switch_Effect_Generator_Name>
    </BehaviorType>

    <BehaviorType Name="SFXBehaviorType">
      <SFXEvent_On_Create> Unit_Select_Masari_Inquisitor_Avenger</SFXEvent_On_Create>
      <SFXEvent_Fire>SFX_Masari_Infantry_Fire </SFXEvent_Fire>
      <SFXEvent_Weapon_Firing_Loop> </SFXEvent_Weapon_Firing_Loop>
      <SFXEvent_Select>Unit_Select_Masari_Inquisitor_Avenger</SFXEvent_Select>
      <SFXEvent_Move>Unit_Move_A_Masari_Inquisitor_Avenger</SFXEvent_Move>
      <SFXEvent_Move_At_Top_Speed>Unit_Move_B_Masari_Inquisitor_Avenger</SFXEvent_Move_At_Top_Speed>
      <SFXEvent_Attack>Unit_Attack_A_Masari_Inquisitor_Avenger</SFXEvent_Attack>
      <SFXEvent_Attack_At_Top_Speed>Unit_Attack_B_Masari_Inquisitor_Avenger</SFXEvent_Attack_At_Top_Speed>
      <SFXEvent_Turret_Rotating_Loop> </SFXEvent_Turret_Rotating_Loop>
      <Death_SFXEvent_Start_Die> Unit_Death_Masari_Male </Death_SFXEvent_Start_Die>
      <SFXEvent_Engine_Idle_Loop> </SFXEvent_Engine_Idle_Loop>
      <SFXEvent_Engine_Moving_Loop> </SFXEvent_Engine_Moving_Loop>
      <SFXEvent_Unit_Lost />
      <SFXEvent_Tactical_Build_Started>GUI_BUILD_Infantry</SFXEvent_Tactical_Build_Started>
      <SFXEvent_Tactical_Build_Complete>Unit_Select_Masari_Inquisitor_Avenger</SFXEvent_Tactical_Build_Complete>
      <SFXEvent_Tactical_Build_Cancelled>GUI_BUILD_Infantry_Canceled</SFXEvent_Tactical_Build_Cancelled>

      <!-- Maria 05.01.2006 - Adding build sounds for Global production -->
      <SFXEvent_Build_Started>GUI_BUILD_Infantry</SFXEvent_Build_Started>
      <SFXEvent_Build_Complete>Unit_Select_Masari_Inquisitor_Avenger</SFXEvent_Build_Complete>
      <SFXEvent_Build_Cancelled>GUI_BUILD_Infantry_Canceled</SFXEvent_Build_Cancelled>
    </BehaviorType>

     <BehaviorType Name="DeathFXBehaviorType">
        <Death_Clone> Damage_Default, Masari_Avenger_Seeker_Death_Clone_Resource </Death_Clone>
     </BehaviorType>
  </X13_Masari_Units>


  <X13_Masari_Units Name="Masari_Avenger_Seeker_Fire">
    <Variant_Of_Existing_Type> Masari_Avenger_Seeker </Variant_Of_Existing_Type>

    <!-- All avengers share this setup, so we'll include it - Oksana 05/21/2007 -->
    <!--INCLUDE ".\Data\XML\Includes\Masari_Avenger\MASARI_INF_Avenger_Light.xml" -->

  </X13_Masari_Units>


  <X13_Masari_Units Name="Masari_Avenger_Seeker_Ice">
    <Variant_Of_Existing_Type> Masari_Avenger_Seeker </Variant_Of_Existing_Type>

    <!-- All avengers share this setup, so we'll include it - Oksana 05/21/2007 -->
    <!--INCLUDE ".\Data\XML\Includes\Masari_Avenger\MASARI_INF_Avenger_Dark.xml" -->

  </X13_Masari_Units>


   <X13_Masari_Units Name="Masari_Avenger_Seeker_Death_Clone_Resource">
      <Variant_Of_Existing_Type>Masari_Avenger_Seeker</Variant_Of_Existing_Type>
      <Use_Base_Type_By_Default> false </Use_Base_Type_By_Default>
      <Is_Placed_By_Editor>false</Is_Placed_By_Editor>

      <CategoryMask> Resource_INST </CategoryMask>
      <LandBehavior>
         HIDE_WHEN_FOGGED,
         BALLISTIC,
         RESOURCE,
         EFFECT_REGISTRY,
         ATTRIBUTE_DIRECTORY
      </LandBehavior>

      <BehaviorType Name="ResourceBehaviorType">
         <Resource_Units> 10 </Resource_Units>
         <Resource_For_Faction> Alien, Alien_ZM06_KamalRex </Resource_For_Faction>
         <Is_Single_Resource> true </Is_Single_Resource>
         <Use_Death_Behavior> true </Use_Death_Behavior>
      </BehaviorType>

    <BehaviorType Name="SFXBehaviorType">
		 <SFXEvent_On_Create> None </SFXEvent_On_Create>
       <Death_SFXEvent_Start_Die> Unit_Death_Masari_Male </Death_SFXEvent_Start_Die>
    </BehaviorType>

   </X13_Masari_Units>





   <!-- **************************************************************************************** -->
  <!-- *****                              SENTRY                                      ********* -->
  <!-- **************************************************************************************** -->
  <X13_Masari_Units Name="Masari_Avenger_Sentry">
    <Variant_Of_Existing_Type> Masari_Male_Avenger </Variant_Of_Existing_Type>

    <!-- TEXT -->
    <Text_ID>TEXT_UNIT_MASARI_AVENGER_SENTRY </Text_ID>


    <!-- ATTRIBUTES -->
    <Attributes SubObjectList="Yes">
      <Regenerate_Type>Masari_Sentry</Regenerate_Type>
    </Attributes>


    <BehaviorType Name="TooltipBehaviorType">
      <Tooltip_Description_Text_ID> TEXT_TOOLTIP_DESCRIPTION_MASARI_AVENGER_SENTRY_LIGHT </Tooltip_Description_Text_ID>
    </BehaviorType>


    <BehaviorType Name="ElementalModeType">
      <Elemental_Object_Types> Fire, Masari_Avenger_Sentry_Fire </Elemental_Object_Types>
      <Elemental_Object_Types> Ice, Masari_Avenger_Sentry_Ice </Elemental_Object_Types>
    </BehaviorType>

    <BehaviorType Name="TypeSwitchBehaviorType">
      <!-- List of types this object can switch to - This is mainly needed to inforce build limits and must be
						      only added to the base type used for production dependencies purposes -->
      <Type_Switch_Types> Masari_Avenger_Sentry_Fire, Masari_Avenger_Sentry_Ice  </Type_Switch_Types>
      <Switch_Effect_Generator_Name> MasariSwitchGenerator </Switch_Effect_Generator_Name>
    </BehaviorType>

    <BehaviorType Name="SFXBehaviorType">
      <SFXEvent_On_Create> Unit_Move_A_Masari_Sentry_Avenger</SFXEvent_On_Create>
      <SFXEvent_Fire> SFX_Masari_Infantry_Fire </SFXEvent_Fire>
      <SFXEvent_Weapon_Firing_Loop>  </SFXEvent_Weapon_Firing_Loop>
      <SFXEvent_Select>Unit_Select_Masari_Sentry_Avenger</SFXEvent_Select>
      <SFXEvent_Move>Unit_Move_A_Masari_Sentry_Avenger</SFXEvent_Move>
      <SFXEvent_Move_At_Top_Speed>Unit_Move_B_Masari_Sentry_Avenger</SFXEvent_Move_At_Top_Speed>
      <SFXEvent_Attack>Unit_Attack_A_Masari_Sentry_Avenger</SFXEvent_Attack>
      <SFXEvent_Attack_At_Top_Speed>Unit_Attack_B_Masari_Sentry_Avenger</SFXEvent_Attack_At_Top_Speed>
      <SFXEvent_Turret_Rotating_Loop> </SFXEvent_Turret_Rotating_Loop>
      <Death_SFXEvent_Start_Die> Unit_Death_Masari_Male </Death_SFXEvent_Start_Die>
      <SFXEvent_Engine_Idle_Loop> </SFXEvent_Engine_Idle_Loop>
      <SFXEvent_Engine_Moving_Loop> </SFXEvent_Engine_Moving_Loop>
      <SFXEvent_Unit_Lost />
      <SFXEvent_Tactical_Build_Started>GUI_BUILD_Infantry</SFXEvent_Tactical_Build_Started>
      <SFXEvent_Tactical_Build_Complete>Unit_Select_Masari_Sentry_Avenger</SFXEvent_Tactical_Build_Complete>
      <SFXEvent_Tactical_Build_Cancelled>GUI_BUILD_Infantry_Canceled</SFXEvent_Tactical_Build_Cancelled>

      <!-- Maria 05.01.2006 - Adding build sounds for Global production -->
      <SFXEvent_Build_Started>GUI_BUILD_Infantry</SFXEvent_Build_Started>
      <SFXEvent_Build_Complete>Unit_Select_Masari_Sentry_Avenger</SFXEvent_Build_Complete>
      <SFXEvent_Build_Cancelled>GUI_BUILD_Infantry_Canceled</SFXEvent_Build_Cancelled>
    </BehaviorType>

     <BehaviorType Name="DeathFXBehaviorType">
        <Death_Clone> Damage_Default, Masari_Avenger_Sentry_Death_Clone_Resource </Death_Clone>
     </BehaviorType>
  </X13_Masari_Units>


  <X13_Masari_Units Name="Masari_Avenger_Sentry_Fire">
    <Variant_Of_Existing_Type> Masari_Avenger_Sentry </Variant_Of_Existing_Type>

    <!-- All avengers share this setup, so we'll include it - Oksana 05/21/2007 -->
    <!--INCLUDE ".\Data\XML\Includes\Masari_Avenger\MASARI_INF_Avenger_Light.xml" -->

  </X13_Masari_Units>


  <X13_Masari_Units Name="Masari_Avenger_Sentry_Ice">
    <Variant_Of_Existing_Type> Masari_Avenger_Sentry </Variant_Of_Existing_Type>

    <!-- All avengers share this setup, so we'll include it - Oksana 05/21/2007 -->
    <!--INCLUDE ".\Data\XML\Includes\Masari_Avenger\MASARI_INF_Avenger_Dark.xml" -->

  </X13_Masari_Units>


   <X13_Masari_Units Name="Masari_Avenger_Sentry_Death_Clone_Resource">
      <Variant_Of_Existing_Type>Masari_Avenger_Sentry</Variant_Of_Existing_Type>
      <Use_Base_Type_By_Default> false </Use_Base_Type_By_Default>
      <Is_Placed_By_Editor>false</Is_Placed_By_Editor>

      <CategoryMask> Resource_INST </CategoryMask>
      <LandBehavior>
         HIDE_WHEN_FOGGED,
         BALLISTIC,
         RESOURCE,
         EFFECT_REGISTRY,
         ATTRIBUTE_DIRECTORY
      </LandBehavior>

      <BehaviorType Name="ResourceBehaviorType">
         <Resource_Units> 10 </Resource_Units>
         <Resource_For_Faction> Alien, Alien_ZM06_KamalRex </Resource_For_Faction>
         <Is_Single_Resource> true </Is_Single_Resource>
         <Use_Death_Behavior> true </Use_Death_Behavior>
      </BehaviorType>

    <BehaviorType Name="SFXBehaviorType">
		 <SFXEvent_On_Create> None </SFXEvent_On_Create>
       <Death_SFXEvent_Start_Die> Unit_Death_Masari_Male </Death_SFXEvent_Start_Die>
    </BehaviorType>

   </X13_Masari_Units>




   <!-- **************************************************************************************** -->
  <!-- *****                              SKYLORD                                     ********* -->
  <!-- **************************************************************************************** -->
  <X13_Masari_Units Name="Masari_Avenger_Skylord">
     <Variant_Of_Existing_Type> Masari_Female_Avenger </Variant_Of_Existing_Type>

     <!-- TEXT -->
     <Text_ID>TEXT_UNIT_MASARI_AVENGER_SKY_LORD </Text_ID>


     <!-- ATTRIBUTES -->
     <Attributes SubObjectList="Yes">
        <Regenerate_Type>Masari_Skylord</Regenerate_Type>
     </Attributes>


     <BehaviorType Name="TooltipBehaviorType">
        <Tooltip_Description_Text_ID> TEXT_TOOLTIP_DESCRIPTION_MASARI_AVENGER_SKY_LORD_DARK </Tooltip_Description_Text_ID>
     </BehaviorType>


     <BehaviorType Name="ElementalModeType">
        <Elemental_Object_Types> Fire, Masari_Avenger_Skylord_Fire </Elemental_Object_Types>
        <Elemental_Object_Types> Ice, Masari_Avenger_Skylord_Ice </Elemental_Object_Types>
     </BehaviorType>

     <BehaviorType Name="TypeSwitchBehaviorType">
        <!-- List of types this object can switch to - This is mainly needed to inforce build limits and must be
						      only added to the base type used for production dependencies purposes -->
        <Type_Switch_Types> Masari_Avenger_Skylord_Fire, Masari_Avenger_Skylord_Ice  </Type_Switch_Types>
        <Switch_Effect_Generator_Name> MasariSwitchGenerator </Switch_Effect_Generator_Name>
     </BehaviorType>

     <BehaviorType Name="SFXBehaviorType">
        <SFXEvent_On_Create> Unit_Select_Masari_Skylord_Avenger </SFXEvent_On_Create>
        <SFXEvent_Fire> SFX_Masari_Infantry_Fire </SFXEvent_Fire>
        <SFXEvent_Weapon_Firing_Loop> </SFXEvent_Weapon_Firing_Loop>
        <SFXEvent_Select>Unit_Select_Masari_Skylord_Avenger</SFXEvent_Select>
        <SFXEvent_Move>Unit_Move_A_Masari_Skylord_Avenger</SFXEvent_Move>
        <SFXEvent_Move_At_Top_Speed>Unit_Move_B_Masari_Skylord_Avenger</SFXEvent_Move_At_Top_Speed>
        <SFXEvent_Attack>Unit_Attack_A_Masari_Skylord_Avenger</SFXEvent_Attack>
        <SFXEvent_Attack_At_Top_Speed>Unit_Attack_B_Masari_Skylord_Avenger</SFXEvent_Attack_At_Top_Speed>
        <SFXEvent_Turret_Rotating_Loop> </SFXEvent_Turret_Rotating_Loop>
        <Death_SFXEvent_Start_Die> Unit_Death_Masari_Male </Death_SFXEvent_Start_Die>
        <SFXEvent_Engine_Idle_Loop> </SFXEvent_Engine_Idle_Loop>
        <SFXEvent_Engine_Moving_Loop> </SFXEvent_Engine_Moving_Loop>
        <SFXEvent_Unit_Lost />
        <SFXEvent_Tactical_Build_Started>GUI_BUILD_Infantry</SFXEvent_Tactical_Build_Started>
        <SFXEvent_Tactical_Build_Complete>Unit_Select_Masari_Skylord_Avenger</SFXEvent_Tactical_Build_Complete>
        <SFXEvent_Tactical_Build_Cancelled>GUI_BUILD_Infantry_Canceled</SFXEvent_Tactical_Build_Cancelled>

        <!-- Maria 05.01.2006 - Adding build sounds for Global production -->
        <SFXEvent_Build_Started>GUI_BUILD_Infantry</SFXEvent_Build_Started>
        <SFXEvent_Build_Complete>Unit_Select_Masari_Skylord_Avenger</SFXEvent_Build_Complete>
        <SFXEvent_Build_Cancelled>GUI_BUILD_Infantry_Canceled</SFXEvent_Build_Cancelled>
     </BehaviorType>

     <BehaviorType Name="DeathFXBehaviorType">
        <Death_Clone> Damage_Default, Masari_Avenger_Skylord_Death_Clone_Resource </Death_Clone>
     </BehaviorType>
  </X13_Masari_Units>

  <X13_Masari_Units Name="Masari_Avenger_Skylord_Fire">
    <Variant_Of_Existing_Type> Masari_Avenger_Skylord </Variant_Of_Existing_Type>

    <!-- All avengers share this setup, so we'll include it - Oksana 05/21/2007 -->
    <!--INCLUDE ".\Data\XML\Includes\Masari_Avenger\MASARI_INF_Avenger_Light.xml" -->

  </X13_Masari_Units>

  <X13_Masari_Units Name="Masari_Avenger_Skylord_Ice">
    <Variant_Of_Existing_Type> Masari_Avenger_Skylord </Variant_Of_Existing_Type>

    <!-- All avengers share this setup, so we'll include it - Oksana 05/21/2007 -->
    <!--INCLUDE ".\Data\XML\Includes\Masari_Avenger\MASARI_INF_Avenger_Dark.xml" -->
     
  </X13_Masari_Units>


   <X13_Masari_Units Name="Masari_Avenger_Skylord_Death_Clone_Resource">
      <Variant_Of_Existing_Type>Masari_Avenger_Skylord</Variant_Of_Existing_Type>
      <Use_Base_Type_By_Default> false </Use_Base_Type_By_Default>
      <Is_Placed_By_Editor>false</Is_Placed_By_Editor>

      <CategoryMask> Resource_INST </CategoryMask>
      <LandBehavior>
         HIDE_WHEN_FOGGED,
         BALLISTIC,
         RESOURCE,
         EFFECT_REGISTRY,
         ATTRIBUTE_DIRECTORY
      </LandBehavior>

      <BehaviorType Name="ResourceBehaviorType">
         <Resource_Units> 10 </Resource_Units>
         <Resource_For_Faction> Alien, Alien_ZM06_KamalRex </Resource_For_Faction>
         <Is_Single_Resource> true </Is_Single_Resource>
         <Use_Death_Behavior> true </Use_Death_Behavior>
      </BehaviorType>

    <BehaviorType Name="SFXBehaviorType">
		 <SFXEvent_On_Create> None </SFXEvent_On_Create>
       <Death_SFXEvent_Start_Die> Unit_Death_Masari_Male </Death_SFXEvent_Start_Die>
    </BehaviorType>

   </X13_Masari_Units>



  <!-- **************************************************************************************** -->
  <!-- *****                              ENFORCER                                    ********* -->
  <!-- **************************************************************************************** -->
  <X13_Masari_Units Name="Masari_Avenger_Enforcer">
    <Variant_Of_Existing_Type> Masari_Male_Avenger </Variant_Of_Existing_Type>

    <!-- TEXT -->
    <Text_ID>TEXT_UNIT_MASARI_AVENGER_ENFORCER </Text_ID>


    <!-- ATTRIBUTES -->
    <Attributes SubObjectList="Yes">
      <Regenerate_Type>Masari_Enforcer</Regenerate_Type>
    </Attributes>


    <BehaviorType Name="TooltipBehaviorType">
      <Tooltip_Description_Text_ID> TEXT_TOOLTIP_DESCRIPTION_MASARI_AVENGER_ENFORCER_LIGHT </Tooltip_Description_Text_ID>
    </BehaviorType>


    <BehaviorType Name="ElementalModeType">
      <Elemental_Object_Types> Fire, Masari_Avenger_Enforcer_Fire </Elemental_Object_Types>
      <Elemental_Object_Types> Ice, Masari_Avenger_Enforcer_Ice </Elemental_Object_Types>
    </BehaviorType>

    <BehaviorType Name="TypeSwitchBehaviorType">
      <!-- List of types this object can switch to - This is mainly needed to inforce build limits and must be
						      only added to the base type used for production dependencies purposes -->
      <Type_Switch_Types> Masari_Avenger_Enforcer_Fire, Masari_Avenger_Enforcer_Ice  </Type_Switch_Types>
      <Switch_Effect_Generator_Name> MasariSwitchGenerator </Switch_Effect_Generator_Name>
    </BehaviorType>

    <BehaviorType Name="SFXBehaviorType">
      <SFXEvent_On_Create> Unit_Select_Masari_Conqueror_Avenger </SFXEvent_On_Create>
      <SFXEvent_Fire> SFX_Masari_Infantry_Fire </SFXEvent_Fire>
      <SFXEvent_Weapon_Firing_Loop> </SFXEvent_Weapon_Firing_Loop>
      <SFXEvent_Select>Unit_Select_Masari_Conqueror_Avenger</SFXEvent_Select>
      <SFXEvent_Move>Unit_Move_A_Masari_Conqueror_Avenger</SFXEvent_Move>
      <SFXEvent_Move_At_Top_Speed>Unit_Move_B_Masari_Conqueror_Avenger</SFXEvent_Move_At_Top_Speed>
      <SFXEvent_Attack>Unit_Attack_A_Masari_Conqueror_Avenger</SFXEvent_Attack>
      <SFXEvent_Attack_At_Top_Speed>Unit_Attack_B_Masari_Conqueror_Avenger</SFXEvent_Attack_At_Top_Speed>
      <SFXEvent_Turret_Rotating_Loop> </SFXEvent_Turret_Rotating_Loop>
      <Death_SFXEvent_Start_Die> Unit_Death_Masari_Male </Death_SFXEvent_Start_Die>
      <SFXEvent_Engine_Idle_Loop> </SFXEvent_Engine_Idle_Loop>
      <SFXEvent_Engine_Moving_Loop> </SFXEvent_Engine_Moving_Loop>
      <SFXEvent_Unit_Lost />
      <SFXEvent_Tactical_Build_Started>GUI_BUILD_Infantry</SFXEvent_Tactical_Build_Started>
      <SFXEvent_Tactical_Build_Complete>Unit_Select_Masari_Conqueror_Avenger</SFXEvent_Tactical_Build_Complete>
      <SFXEvent_Tactical_Build_Cancelled>GUI_BUILD_Infantry_Canceled</SFXEvent_Tactical_Build_Cancelled>

      <!-- Maria 05.01.2006 - Adding build sounds for Global production -->
      <SFXEvent_Build_Started>GUI_BUILD_Infantry</SFXEvent_Build_Started>
      <SFXEvent_Build_Complete>Unit_Select_Masari_Conqueror_Avenger</SFXEvent_Build_Complete>
      <SFXEvent_Build_Cancelled>GUI_BUILD_Infantry_Canceled</SFXEvent_Build_Cancelled>
    </BehaviorType>
     
     <BehaviorType Name="DeathFXBehaviorType">
        <Death_Clone> Damage_Default, Masari_Avenger_Enforcer_Death_Clone_Resource </Death_Clone>
     </BehaviorType>
  </X13_Masari_Units>


  <X13_Masari_Units Name="Masari_Avenger_Enforcer_Fire">
    <Variant_Of_Existing_Type> Masari_Avenger_Enforcer </Variant_Of_Existing_Type>

    <!-- All avengers share this setup, so we'll include it - Oksana 05/21/2007 -->
    <!--INCLUDE ".\Data\XML\Includes\Masari_Avenger\MASARI_INF_Avenger_Light.xml" -->

  </X13_Masari_Units>


  <X13_Masari_Units Name="Masari_Avenger_Enforcer_Ice">
    <Variant_Of_Existing_Type> Masari_Avenger_Enforcer </Variant_Of_Existing_Type>

    <!-- All avengers share this setup, so we'll include it - Oksana 05/21/2007 -->
    <!--INCLUDE ".\Data\XML\Includes\Masari_Avenger\MASARI_INF_Avenger_Dark.xml" -->

  </X13_Masari_Units>


   <X13_Masari_Units Name="Masari_Avenger_Enforcer_Death_Clone_Resource">
      <Variant_Of_Existing_Type>Masari_Avenger_Enforcer</Variant_Of_Existing_Type>
      <Use_Base_Type_By_Default> false </Use_Base_Type_By_Default>
      <Is_Placed_By_Editor>false</Is_Placed_By_Editor>

      <CategoryMask> Resource_INST </CategoryMask>
      <LandBehavior>
         HIDE_WHEN_FOGGED,
         BALLISTIC,
         RESOURCE,
         EFFECT_REGISTRY,
         ATTRIBUTE_DIRECTORY
      </LandBehavior>

      <BehaviorType Name="ResourceBehaviorType">
         <Resource_Units> 10 </Resource_Units>
         <Resource_For_Faction> Alien, Alien_ZM06_KamalRex </Resource_For_Faction>
         <Is_Single_Resource> true </Is_Single_Resource>
         <Use_Death_Behavior> true </Use_Death_Behavior>
      </BehaviorType>

    <BehaviorType Name="SFXBehaviorType">
		 <SFXEvent_On_Create> None </SFXEvent_On_Create>
       <Death_SFXEvent_Start_Die> Unit_Death_Masari_Male </Death_SFXEvent_Start_Die>
    </BehaviorType>

   </X13_Masari_Units>



	<!-- **************************************************************************************** -->
	<!-- *** PROJECTILES ************************************************************************ -->
	<!-- **************************************************************************************** -->


	<Projectile Name="Proj_Masari_Avenger_Light_Bolt">

		<!-- ART -->
		<Land_Model_Name>Laser_Masari_Avenger_Light_Bolt</Land_Model_Name> <!-- Defined in LASERBEAMS.XML -->
		<AssetBank> BANK_MASARI </AssetBank>

		<!-- INTERFACE -->
		<Text_ID>TEXT_NONE</Text_ID>
		<Is_Placed_By_Editor>false</Is_Placed_By_Editor>

		<!-- MOVEMENT -->
		<Max_Speed>9.0</Max_Speed>
		<Max_Rate_Of_Turn>0.0</Max_Rate_Of_Turn>
		<AI_Combat_Power>200</AI_Combat_Power>

		<!-- BEHAVIORS-->
		<Behavior>PROJECTILE, HIDE_WHEN_FOGGED, EFFECT_GENERATOR </Behavior>

		<BehaviorType Name="ArmorAndDamageBehaviorType">
			<Damage_Type> Damage_Masari_Avenger_Weapon </Damage_Type>
		</BehaviorType>

		<BehaviorType Name="ProjectileBehaviorType">
			<Projectile_Damages_Random_Hard_Points>No</Projectile_Damages_Random_Hard_Points>
			<Projectile_Category>DEFAULT</Projectile_Category>

			<Projectile_Max_Flight_Distance>5000.0</Projectile_Max_Flight_Distance>
			<Projectile_Damage>4</Projectile_Damage>
			<Projectile_Does_Shield_Damage>True</Projectile_Does_Shield_Damage>
			<Projectile_Does_Hitpoint_Damage>Yes</Projectile_Does_Hitpoint_Damage>
			<Projectile_Object_Detonation_Particle>Masari_Avenger_Light_detonation</Projectile_Object_Detonation_Particle>
			<Projectile_Object_Armor_Reduced_Detonation_Particle>Masari_Avenger_Light_detonation</Projectile_Object_Armor_Reduced_Detonation_Particle>
			<Projectile_Ground_Detonation_Particle>Masari_Avenger_Light_detonation</Projectile_Ground_Detonation_Particle>
			<Projectile_Lifetime_Detonation_Particle>Masari_Avenger_Light_Miss</Projectile_Lifetime_Detonation_Particle>
         <Projectile_Absorbed_By_Shields_Particle>Masari_Avenger_Light_Miss</Projectile_Absorbed_By_Shields_Particle>
			<Projectile_SFXEvent_Detonate> SFX_Masari_Detonation_1 </Projectile_SFXEvent_Detonate>
			<Projectile_SFXEvent_Detonate_Reduced_By_Armor> SFX_Masari_Small_Damage_Detonation </Projectile_SFXEvent_Detonate_Reduced_By_Armor>
			<Impact_Effect_Generator_Name> PurifyingLightImpactGenerator </Impact_Effect_Generator_Name>
		</BehaviorType>

		<Effect_Generator_Data SubObjectList="Yes">

			<!-- Standard Purifying Light generator - Jeff P 07/09/2007 -->
			<!--INCLUDE ".\Data\XML\Includes\Masari_Impact_Generators\MASARI_Purifying_Light_Generator.xml" -->

		</Effect_Generator_Data>

	</Projectile>



	<Projectile Name="Proj_Masari_Avenger_Dark">

		<!-- ART -->
		<Land_Model_Name>Laser_Masari_Avenger_Dark_Bolt</Land_Model_Name> <!-- Defined in LASERBEAMS.XML -->
		<AssetBank> BANK_MASARI </AssetBank>

		<!-- INTERFACE -->
		<Text_ID>TEXT_NONE</Text_ID>
		<Is_Placed_By_Editor>false</Is_Placed_By_Editor>

		<!-- MOVEMENT -->
		<Max_Speed>9.0</Max_Speed>
		<Max_Rate_Of_Turn>0.0</Max_Rate_Of_Turn>
		<AI_Combat_Power>200</AI_Combat_Power>

		<!-- BEHAVIORS-->
		<Behavior>PROJECTILE, HIDE_WHEN_FOGGED, EFFECT_GENERATOR </Behavior>

		<BehaviorType Name="ArmorAndDamageBehaviorType">
			<Damage_Type> Damage_Masari_Avenger_Weapon </Damage_Type>
		</BehaviorType>

		<BehaviorType Name="ProjectileBehaviorType">
			<Projectile_Damages_Random_Hard_Points>No</Projectile_Damages_Random_Hard_Points>
			<Projectile_Category>DEFAULT</Projectile_Category>
			<Projectile_Max_Flight_Distance>5000.0</Projectile_Max_Flight_Distance>
			<Projectile_Damage>4</Projectile_Damage>
			<Projectile_Does_Shield_Damage>Yes</Projectile_Does_Shield_Damage>
			<Projectile_Does_Hitpoint_Damage>Yes</Projectile_Does_Hitpoint_Damage>
			<Projectile_Object_Detonation_Particle>Masari_Avenger_Dark_detonation</Projectile_Object_Detonation_Particle>
			<Projectile_Object_Armor_Reduced_Detonation_Particle>Masari_Avenger_Dark_detonation</Projectile_Object_Armor_Reduced_Detonation_Particle>
			<Projectile_Ground_Detonation_Particle>Masari_Avenger_Dark_Miss</Projectile_Ground_Detonation_Particle>
			<Projectile_Lifetime_Detonation_Particle>Masari_Avenger_Dark_Miss</Projectile_Lifetime_Detonation_Particle>
         <Projectile_Absorbed_By_Shields_Particle>Masari_Avenger_Dark_Miss</Projectile_Absorbed_By_Shields_Particle>
			<Projectile_SFXEvent_Detonate> SFX_Masari_Detonation_1 </Projectile_SFXEvent_Detonate>
			<Projectile_SFXEvent_Detonate_Reduced_By_Armor> SFX_Masari_Small_Damage_Detonation </Projectile_SFXEvent_Detonate_Reduced_By_Armor>
			<Impact_Effect_Generator_Name> CripplingShotsImpactGenerator </Impact_Effect_Generator_Name>
		</BehaviorType>

		<Effect_Generator_Data SubObjectList="Yes">

			<!-- Standard Crippling Shots - Jeff P 06/13/2007 -->
			<!--INCLUDE ".\Data\XML\Includes\Masari_Impact_Generators\MASARI_Crippling_Shots_Generator.xml" -->

		</Effect_Generator_Data>

	</Projectile>



</Masari_INF_Avenger_XML>
