<?xml version="1.0" encoding="utf-8"?>
<Effects>

	<!-- DestroyPatchObjectEffect : Destroy the object (not by damage as patches have no health) -->
	<Effect Name="DestroyPatchObjectEffect">
		<Effect_Class> DestroyPatch </Effect_Class>
		<Duration> 1.0 </Duration>
		<Extends_Same_Source_Duration_Only>false</Extends_Same_Source_Duration_Only>
		<Extends_Existing_Duration> false </Extends_Existing_Duration>
		<Allow_Same_Source_Stacking> true </Allow_Same_Source_Stacking>

		<Effect_Component Type="Destroy">
		</Effect_Component>

	</Effect>

	<!-- NovusPatchTimeOutEffect : Used to turn off a generator after it times out -->
	<Effect Name="NovusPatchTimeOutEffect">
		<Effect_Class> Transparent </Effect_Class>
		<Duration> 1.0 </Duration>
		<Extends_Same_Source_Duration_Only>false</Extends_Same_Source_Duration_Only>
		<Extends_Existing_Duration> false </Extends_Existing_Duration>
		<Allow_Same_Source_Stacking> true </Allow_Same_Source_Stacking>

		<Effect_Component Type="ApplyEffectOnRemove">
         <Effect_Name> DestroyPatchObjectEffect </Effect_Name>
         <Apply_On_Expiration_Only> false </Apply_On_Expiration_Only>
      </Effect_Component>
		
	</Effect>

	<!-- Radiation Casing: All units and structures take 25% less damage from radiation for the duration. -->
	<Effect Name="NovusPatchRadiationCasingEffect">
		<Effect_Class> PatchRadiationCasing </Effect_Class>
		<Duration> -1.0 </Duration>
		<CategoryMask> CanBeRemovedByAbility</CategoryMask>

		<Effect_Component Type="ModifyArmor">
			<!-- reduce radiation damage by 50%, this could drop it to Zero -->
			<Amount> -0.50 </Amount>
			<Damage_Type> Damage_Alien_AE_Radiation </Damage_Type>
		</Effect_Component>
	</Effect>


	<Effect Name="NovusRadiationCasingVisualEffectSmall">
		<Effect_Class> Transparent </Effect_Class>
		<Duration> -1.0 </Duration>
		<CategoryMask> CanBeRemovedByAbility</CategoryMask>

		<Effect_Component Type="ParticleSystem">
			<Particle_System_Type> Novus_Patch_Radiation_Shield_Small </Particle_System_Type>
		</Effect_Component>

	</Effect>

	
	<Effect Name="NovusRadiationCasingVisualEffectLarge">
		<Effect_Class> Transparent </Effect_Class>
		<Duration> -1.0 </Duration>
		<CategoryMask> CanBeRemovedByAbility</CategoryMask>

		<Effect_Component Type="ParticleSystem">
			<Particle_System_Type> Novus_Patch_Radiation_Shield_Large </Particle_System_Type>
		</Effect_Component>

	</Effect>
	
	
	
	
	<!-- Coolant Boost: All units and structures take 25% less damage from heat-based attacks for the duration. -->
	<Effect Name="NovusPatchCoolantBoostEffect">
		<Effect_Class> PatchCoolantBoost </Effect_Class>
		<Duration> -1.0 </Duration>
		<CategoryMask> CanBeRemovedByAbility</CategoryMask>

		<Effect_Component Type="ModifyArmor">
			<!-- reduce heat damage by 50%, -->
			<Amount> -0.50 </Amount>
			<Damage_Type> Damage_Fire </Damage_Type>
		</Effect_Component>
		
	</Effect>

	
	<Effect Name="NovusCoolantBoostVisualEffectSmall">
		<Effect_Class> Transparent </Effect_Class>
		<Duration> -1.0 </Duration>
		<CategoryMask> CanBeRemovedByAbility</CategoryMask>

		<Effect_Component Type="ParticleSystem">
			<Particle_System_Type> Novus_Patch_Coolant_Boost_Small </Particle_System_Type>
		</Effect_Component>

	</Effect>


	<Effect Name="NovusCoolantBoostVisualEffectLarge">
		<Effect_Class> Transparent </Effect_Class>
		<Duration> -1.0 </Duration>
		<CategoryMask> CanBeRemovedByAbility</CategoryMask>

		<Effect_Component Type="ParticleSystem">
			<Particle_System_Type> Novus_Patch_Coolant_Boost_Large </Particle_System_Type>
		</Effect_Component>

	</Effect>
	
	
	
	
	
	
	
	<!-- Overclocking: All units move and fire 35% faster while Overclocking is in effect. Damage taken is doubled. -->
	<Effect Name="NovusPatchOverclockEffect">
		<Effect_Class> PatchOverclock </Effect_Class>
		<Duration> -1.0 </Duration>
		<CategoryMask> CanBeRemovedByAbility</CategoryMask>

		<Effect_Component Type="AttributeModifier">
			<Attribute> Max_Speed_Mult_Coeff </Attribute>
			<Modifier_Value> 0.25 </Modifier_Value>
		</Effect_Component>

		<Effect_Component Type="AttributeModifier">
			<Attribute> Weapon_Rate_Multiplier </Attribute>
			<Modifier_Value> 0.65 </Modifier_Value>
		</Effect_Component>

		<Effect_Component Type="AttributeModifier">
			<Attribute> Damage_Taken_Mult_Coeff </Attribute>
			<Modifier_Value> 0.50 </Modifier_Value>
		</Effect_Component>
	</Effect>


	<Effect Name="NovusOverclockVisualEffectSmall">
		<Effect_Class> Transparent </Effect_Class>
		<Duration> -1.0 </Duration>
		<CategoryMask> CanBeRemovedByAbility</CategoryMask>

		<Effect_Component Type="ParticleSystem">
			<Particle_System_Type> Novus_Patch_Overclock_Small </Particle_System_Type>
		</Effect_Component>

	</Effect>


	<Effect Name="NovusOverclockVisualEffectLarge">
		<Effect_Class> Transparent </Effect_Class>
		<Duration> -1.0 </Duration>
		<CategoryMask> CanBeRemovedByAbility</CategoryMask>

		<Effect_Component Type="ParticleSystem">
			<Particle_System_Type> Novus_Patch_Overclock_Large </Particle_System_Type>
		</Effect_Component>

	</Effect>
	
	
	
	
	
	<!-- Optimized Assembly: All units build at 200% speed for the duration. -->
	<Effect Name="NovusPatchOptimizedAssemblyEffect">
		<Effect_Class> PatchOptimizedAssembly </Effect_Class>
		<Duration> -1.0 </Duration>
		<CategoryMask> CanBeRemovedByAbility</CategoryMask>

		<Effect_Component Type="AttributeModifier">
			<Attribute> Unit_Build_Rate_Multiplier </Attribute>
			<!-- +100% build rate -->
			<Modifier_Value> 1.0 </Modifier_Value>
		</Effect_Component>
	</Effect>

	

	<!-- Backup Systems: All units and structures gain an additional 18% health (delivered full) for the duration. -->
	<Effect Name="NovusPatchBackupSystemsEffect">
		<Effect_Class> PatchBackupSystems</Effect_Class>
		<Duration> -1.0 </Duration>
		<CategoryMask> CanBeRemovedByAbility</CategoryMask>

      <Effect_Component Type="MaxHealth">
         <Modifier_Value> 0.18 </Modifier_Value>
         <Adjust_Health_By_Same_Percent>Yes</Adjust_Health_By_Same_Percent>
      </Effect_Component>
      
		<!--<Effect_Component Type="AttributeModifier">
			<Attribute> Unit_Extra_Health_Multiplier </Attribute>
			--><!-- 2x health --><!--
			<Modifier_Value> 0.18 </Modifier_Value>
		</Effect_Component>

		<Effect_Component Type="Heal">
			--><!-- heals 50% of unit i.e. enough to heal what we just added --><!--
			<Percent_Heal> 0.18 </Percent_Heal>
		</Effect_Component>-->
	</Effect>

	
	
	<!-- Emergency Power: Instantly brings all structures on-line regardless of current powered state for the duration. -->
	<Effect Name="NovusPatchEmergencyPowerEffect">
		<Effect_Class> PatchEmergencyPower </Effect_Class>
		<Duration> 30.0 </Duration>
		<Effect_Component Type="AttributeModifier">
			<Attribute> Is_Powered </Attribute>
			<!-- A bitwise Or with value 1 will force the attribute to "true" for the duration. -->
			<Modifier_Integer_Value> 1 </Modifier_Integer_Value>
			<Modifier_Type> Bitwise_Or </Modifier_Type>
		</Effect_Component>

		<Effect_Component Type="AttributeModifier">
			<Attribute> Powered_By_Patch </Attribute>
			<Modifier_Value> 1 </Modifier_Value>
		</Effect_Component>

	</Effect>

	
	
	<!-- Extrapolation: All units and structures increase sight range by 100% for the duration. -->
	<Effect Name="NovusPatchExtrapolationEffect">
		<Effect_Class> PatchExtrapolation </Effect_Class>
		<Duration> -1.0 </Duration>
		<CategoryMask> CanBeRemovedByAbility</CategoryMask>

		<Effect_Component Type="AttributeModifier">
			<Attribute> Max_Land_FOW_Reveal_Mult_Coeff </Attribute>
			<!-- 25% vision -->
			<Modifier_Value> 0.25 </Modifier_Value>
		</Effect_Component>
	</Effect>

	
	
	<!-- Spectrum Cycle: All units and structures gain cloaking detection at their sight range for the duration. -->
	<Effect Name="NovusPatchSpectrumCycleEffect">
		<Effect_Class> PatchSpectrumCycle </Effect_Class>
		<Duration> -1.0 </Duration>
		<CategoryMask> CanBeRemovedByAbility</CategoryMask>
		
		<Effect_Component Type="ApplyGenerator">
			<Effect_Generator_Name> NovusPatchGrantedSpectrumCycleEffectGenerator </Effect_Generator_Name>
		</Effect_Component>
	
	</Effect>


	<Effect Name="NovusSpectrumCycleVisualEffectSmall">
		<Effect_Class> Transparent </Effect_Class>
		<Duration> -1.0 </Duration>
		<CategoryMask> CanBeRemovedByAbility</CategoryMask>

		<Effect_Component Type="ParticleSystem">
			<Particle_System_Type> Novus_Patch_Spectrum_Cycle_Small </Particle_System_Type>
		</Effect_Component>

	</Effect>


	<Effect Name="NovusSpectrumCycleVisualEffectLarge">
		<Effect_Class> Transparent </Effect_Class>
		<Duration> -1.0 </Duration>
		<CategoryMask> CanBeRemovedByAbility</CategoryMask>

		<Effect_Component Type="ParticleSystem">
			<Particle_System_Type> Novus_Patch_Spectrum_Cycle_Large </Particle_System_Type>
		</Effect_Component>

	</Effect>
	
	
	<Effect Name="NovusPatchGrantedSpectrumCycleEffect">
		<Effect_Class> RevealCloaking </Effect_Class>
		<Duration> 2.0 </Duration>
		<CategoryMask> CanBeRemovedByAbility</CategoryMask>
		<Extends_Existing_Duration> true </Extends_Existing_Duration>

		<Effect_Component Type="RemoveEffect">
			<Remove_Effect_Class> Cloaking </Remove_Effect_Class>
		</Effect_Component>

		<Effect_Component Type="BlockEffect">
			<Block_Effect_Class> Cloaking </Block_Effect_Class>
		</Effect_Component>
	</Effect>

	
	
	
	
	
	
	
	
	
	
	<!-- Optimized Collection: Collecting units gain 25% more much from the same amount of resource for the duration. -->
	<Effect Name="NovusPatchOptimizedCollectionEffect">
		<Effect_Class> Transparent </Effect_Class>
		<Duration> -1.0 </Duration>
		<CategoryMask> CanBeRemovedByAbility</CategoryMask>
		<Effect_Component Type="AttributeModifier">
			<Attribute> Collector_Resource_Gain_Multiplier </Attribute>
			<Modifier_Value> 0.25 </Modifier_Value>
		</Effect_Component>
	</Effect>

	<!-- Reboot: Wipes all negative effects from all Novus units and structures. All objects are inactive while rebooting. -->
	<Effect Name="NovusPatchRebootEffect">
		<Effect_Class> Transparent </Effect_Class>
		<Duration> 10.0 </Duration>
		<CategoryMask> CanBeRemovedByAbility</CategoryMask>
		<Extends_Existing_Duration> false </Extends_Existing_Duration>

		<Effect_Component Type="RemoveEffect">
			<Remove_Effect_Class> NovusVirus </Remove_Effect_Class>
		</Effect_Component>

		<Effect_Component Type="RemoveEffect">
			<Remove_Effect_Class> NovusVirusAuraGenerators </Remove_Effect_Class>
		</Effect_Component>

		<Effect_Component Type="DisableAbility">
			<Abilities/>
		</Effect_Component>

		<Effect_Component Type="DisableBehavior">
			<Behaviors> TEAM_TARGETING, TARGETING, WEAPON, TURRET, WALK_LOCOMOTOR, VTOL_LOCOMOTOR, UNIT_ABILITY, POWERED </Behaviors>
		</Effect_Component>

      <Effect_Component Type="Animate">
         <Animation_Type>Anim_Idle </Animation_Type>
         <Unapply_When_Finished>No</Unapply_When_Finished>
         <Is_Looping>Yes</Is_Looping>
         <Blend_Time>0.03</Blend_Time>
      </Effect_Component>

		<!-- the following will be redundant in most cases are power is being shut down but there might be somecases these are needed -->
		<Effect_Component Type="AttributeModifier">
         <Attribute> Unit_Build_Rate_Multiplier </Attribute>
         <!-- 500% decrease in build rate i.e should stop production -->
         <Modifier_Value> -5.0 </Modifier_Value>
		</Effect_Component>

		<Effect_Component Type="AttributeModifier">
			<Attribute> Structure_Slow_Build </Attribute>
			<!-- 10000% slow build rate, should bring upgrades and building to a halt -->
			<Modifier_Value> 1000.0 </Modifier_Value>
		</Effect_Component>

		<Effect_Component Type="RemoveEffect">
			<Remove_Effect_Class> MindControl </Remove_Effect_Class>
		</Effect_Component>
      
      <Effect_Component Type="RemoveEffect">
         <Remove_Effect_Class> MindControlVisual </Remove_Effect_Class>
      </Effect_Component>

		<Effect_Component Type="RemoveEffect">
			<Remove_Effect_Class> Burden </Remove_Effect_Class>
		</Effect_Component>

		<Effect_Component Type="RemoveEffect">
			<Remove_Effect_Class> Cloaking </Remove_Effect_Class>
		</Effect_Component>

		<Effect_Component Type="RemoveEffect">
			<Remove_Effect_Class> Mirage </Remove_Effect_Class>
		</Effect_Component>

		<Effect_Component Type="RemoveEffect">
			<Remove_Effect_Class> Phased </Remove_Effect_Class>
		</Effect_Component>

		<Effect_Component Type="BlockEffect">
			<Remove_Effect_Class> Cloaking </Remove_Effect_Class>
		</Effect_Component>

		<Effect_Component Type="BlockEffect">
			<Remove_Effect_Class> Mirage </Remove_Effect_Class>
		</Effect_Component>

		<Effect_Component Type="BlockEffect">
			<Remove_Effect_Class> Phased </Remove_Effect_Class>
		</Effect_Component>

    <Effect_Component Type="AttributeModifier">
      <Attribute> Render_Tint_Red </Attribute>
      <Modifier_Value> -0.6 </Modifier_Value>
    </Effect_Component>

    <Effect_Component Type="AttributeModifier">
      <Attribute> Render_Tint_Green </Attribute>
      <Modifier_Value> -0.6 </Modifier_Value>
    </Effect_Component>

    <Effect_Component Type="AttributeModifier">
      <Attribute> Render_Tint_Blue </Attribute>
      <Modifier_Value> -0.6 </Modifier_Value>
    </Effect_Component>

    <!-- other bad things removed here -->

	</Effect>

	<!-- Reboot: block mind control etc -->
	<Effect Name="NovusPatchRebootBlockEffect">
		<Effect_Class> PatchBlock </Effect_Class>
		<Duration> 10.0 </Duration>
		<CategoryMask> CanBeRemovedByAbility</CategoryMask>
		<Extends_Existing_Duration> false </Extends_Existing_Duration>

		<Effect_Component Type="BlockEffect">
			<Block_Effect_Class> Burden </Block_Effect_Class>
		</Effect_Component>

		<Effect_Component Type="BlockEffect">
			<Block_Effect_Class> MindControl </Block_Effect_Class>
		</Effect_Component>

      <Effect_Component Type="BlockEffect">
			<Block_Effect_Class> MindControlVisual </Block_Effect_Class>
		</Effect_Component>
      
		<Effect_Component Type="BlockEffect">
			<Block_Effect_Class> NovusVirusAuraGenerators </Block_Effect_Class>
		</Effect_Component>

		<Effect_Component Type="BlockEffect">
			<Block_Effect_Class> NovusVirus </Block_Effect_Class>
		</Effect_Component>

	</Effect>

	<!-- Reboot: clear and block mind control etc -->
	<Effect Name="NovusPatchClearMindControlEffect">
		<Effect_Class> ClearMindControl </Effect_Class>
		<Duration> 10.0 </Duration>
		<Extends_Existing_Duration> false </Extends_Existing_Duration>

		<Effect_Component Type="RemoveEffect">
			<Remove_Effect_Class> MindControl </Remove_Effect_Class>
		</Effect_Component>

		<Effect_Component Type="BlockEffect">
			<Block_Effect_Class> MindControl </Block_Effect_Class>
		</Effect_Component>

      <Effect_Component Type="RemoveEffect">
         <Remove_Effect_Class> MindControlVisual </Remove_Effect_Class>
      </Effect_Component>

      <Effect_Component Type="BlockEffect">
			<Block_Effect_Class> MindControlVisual </Block_Effect_Class>
      </Effect_Component>

	</Effect>

	<!-- Viral Cascade: All enemy units under novus signal radius are instantly virally infected. -->
	<Effect Name="NovusPatchViralCascadeEffect">
		<Effect_Class> PatchViralCascadeAura </Effect_Class>
		<Duration> 10.0 </Duration>
		<CategoryMask> CanBeRemovedByAbility</CategoryMask>

		<!-- Apply the ViralCascadeAura effect generator, which will make the target pulse an AE that virally infects nearby enemy objects. -->
		<Effect_Component Type="ApplyGenerator">
			<Effect_Generator_Name> ViralCascadeAuraEffectGenerator </Effect_Generator_Name>
			<Activate_Generator> true </Activate_Generator>
		</Effect_Component>
	</Effect>

	<!-- Viral Reboot: All currently virused enemy units are shut down for 10 seconds. -->
	<Effect Name="NovusPatchViralRebootEffect">
		<Effect_Class> PatchViralReboot </Effect_Class>
		<Duration> 10.0 </Duration>
		<CategoryMask> CanBeRemovedByAbility</CategoryMask>

		<Effect_Component Type="RemoveEffect">
			<Remove_Effect_Class> NovusVirus </Remove_Effect_Class>
		</Effect_Component>

		<Effect_Component Type="RemoveEffect">
			<Remove_Effect_Class> NovusVirusAuraGenerators </Remove_Effect_Class>
		</Effect_Component>

		<Effect_Component Type="ParticleSystem">
			<Particle_System_Type> Novus_Patch_Viral_Reboot_Target_Aura </Particle_System_Type>
		</Effect_Component>

    <Effect_Component Type="AttributeModifier">
      <Attribute> Render_Tint_Red </Attribute>
      <Modifier_Value> -0.6 </Modifier_Value>
    </Effect_Component>

    <Effect_Component Type="AttributeModifier">
      <Attribute> Render_Tint_Green </Attribute>
      <Modifier_Value> -0.6 </Modifier_Value>
    </Effect_Component>

    <Effect_Component Type="AttributeModifier">
      <Attribute> Render_Tint_Blue </Attribute>
      <Modifier_Value> -0.6 </Modifier_Value>
    </Effect_Component>

		<Effect_Component Type="DisableBehavior">
			<Behaviors> TEAM_TARGETING, TARGETING, UNIT_ABILITY, WEAPON, TURRET, WALK_LOCOMOTOR, VTOL_LOCOMOTOR, GIANT_WALK_LOCOMOTOR, TACTICAL_ENABLER, REDIRECT_PROJECTILE </Behaviors>
		</Effect_Component>

		<Effect_Component Type="DisableAbility">
			<Abilities/>
		</Effect_Component>

		<Effect_Component Type="AttributeModifier">
         <Attribute> Unit_Build_Rate_Multiplier </Attribute>
         <!-- 20% decrease in build rate -->
         <Modifier_Value> -0.2 </Modifier_Value>
		</Effect_Component>

		<Effect_Component Type="AttributeModifier">
			<Attribute> Patch_Viral_Reboot </Attribute>
			<Modifier_Value> 1.0 </Modifier_Value>
		</Effect_Component>

	</Effect>




</Effects>
